{
  "session_id": "agent_20260405_024150_t1lrsy",
  "session_type": "agent",
  "start_time_ms": 0,
  "end_time_ms": 2113,
  "user_agent": "Mozilla/5.0 (Windows NT 10.0; Win64; x64) AppleWebKit/537.36 (KHTML, like Gecko) Chrome/145.0.0.0 Safari/537.36",
  "viewport": {
    "width": 1280,
    "height": 800
  },
  "events": [
    {
      "event_id": 1,
      "timestamp_ms": 0,
      "type": "navigation",
      "data": {
        "url": "http://localhost:8001/demo/index.html?session_type=agent",
        "referrer": "",
        "page": "listings"
      }
    },
    {
      "event_id": 2,
      "timestamp_ms": 214,
      "type": "mousemove",
      "data": {
        "path": [
          {
            "x": 795,
            "y": 553,
            "t_ms": 200
          },
          {
            "x": 795,
            "y": 541,
            "t_ms": 214
          }
        ],
        "target_element": "div",
        "target_bbox": {
          "x": 661,
          "y": 442,
          "width": 259,
          "height": 180
        }
      }
    },
    {
      "event_id": 3,
      "timestamp_ms": 221,
      "type": "mousemove",
      "data": {
        "path": [
          {
            "x": 795,
            "y": 541,
            "t_ms": 214
          },
          {
            "x": 795,
            "y": 529,
            "t_ms": 221
          }
        ],
        "target_element": "div",
        "target_bbox": {
          "x": 661,
          "y": 442,
          "width": 259,
          "height": 180
        }
      }
    },
    {
      "event_id": 4,
      "timestamp_ms": 227,
      "type": "mousemove",
      "data": {
        "path": [
          {
            "x": 795,
            "y": 529,
            "t_ms": 221
          },
          {
            "x": 796,
            "y": 477,
            "t_ms": 227
          }
        ],
        "target_element": "div",
        "target_bbox": {
          "x": 661,
          "y": 442,
          "width": 259,
          "height": 180
        }
      }
    },
    {
      "event_id": 5,
      "timestamp_ms": 234,
      "type": "mousemove",
      "data": {
        "path": [
          {
            "x": 796,
            "y": 477,
            "t_ms": 227
          },
          {
            "x": 800,
            "y": 437,
            "t_ms": 234
          }
        ],
        "target_element": "[data-log-id='card-p003']",
        "target_bbox": {
          "x": 633,
          "y": 414,
          "width": 315,
          "height": 404
        }
      }
    },
    {
      "event_id": 6,
      "timestamp_ms": 241,
      "type": "mousemove",
      "data": {
        "path": [
          {
            "x": 800,
            "y": 437,
            "t_ms": 234
          },
          {
            "x": 806,
            "y": 393,
            "t_ms": 241
          }
        ],
        "target_element": "div",
        "target_bbox": {
          "x": 0,
          "y": 334,
          "width": 1265,
          "height": 80
        }
      }
    },
    {
      "event_id": 7,
      "timestamp_ms": 248,
      "type": "mousemove",
      "data": {
        "path": [
          {
            "x": 806,
            "y": 393,
            "t_ms": 241
          },
          {
            "x": 812,
            "y": 353,
            "t_ms": 248
          }
        ],
        "target_element": "div",
        "target_bbox": {
          "x": 0,
          "y": 334,
          "width": 1265,
          "height": 80
        }
      }
    },
    {
      "event_id": 8,
      "timestamp_ms": 256,
      "type": "mousemove",
      "data": {
        "path": [
          {
            "x": 812,
            "y": 353,
            "t_ms": 248
          },
          {
            "x": 818,
            "y": 317,
            "t_ms": 256
          }
        ],
        "target_element": "section",
        "target_bbox": {
          "x": 0,
          "y": 77,
          "width": 1265,
          "height": 257
        }
      }
    },
    {
      "event_id": 9,
      "timestamp_ms": 269,
      "type": "mousemove",
      "data": {
        "path": [
          {
            "x": 818,
            "y": 317,
            "t_ms": 256
          },
          {
            "x": 832,
            "y": 247,
            "t_ms": 269
          }
        ],
        "target_element": "h1",
        "target_bbox": {
          "x": 48,
          "y": 173,
          "width": 1169,
          "height": 128
        }
      }
    },
    {
      "event_id": 10,
      "timestamp_ms": 276,
      "type": "mousemove",
      "data": {
        "path": [
          {
            "x": 832,
            "y": 247,
            "t_ms": 269
          },
          {
            "x": 841,
            "y": 213,
            "t_ms": 276
          }
        ],
        "target_element": "em",
        "target_bbox": {
          "x": 410,
          "y": 166,
          "width": 547,
          "height": 77
        }
      }
    },
    {
      "event_id": 11,
      "timestamp_ms": 283,
      "type": "mousemove",
      "data": {
        "path": [
          {
            "x": 841,
            "y": 213,
            "t_ms": 276
          },
          {
            "x": 848,
            "y": 177,
            "t_ms": 283
          }
        ],
        "target_element": "em",
        "target_bbox": {
          "x": 410,
          "y": 166,
          "width": 547,
          "height": 77
        }
      }
    },
    {
      "event_id": 12,
      "timestamp_ms": 291,
      "type": "mousemove",
      "data": {
        "path": [
          {
            "x": 848,
            "y": 177,
            "t_ms": 283
          },
          {
            "x": 855,
            "y": 146,
            "t_ms": 291
          }
        ],
        "target_element": "div",
        "target_bbox": {
          "x": 48,
          "y": 141,
          "width": 1169,
          "height": 16
        }
      }
    },
    {
      "event_id": 13,
      "timestamp_ms": 547,
      "type": "mousemove",
      "data": {
        "path": [
          {
            "x": 855,
            "y": 146,
            "t_ms": 291
          },
          {
            "x": 858,
            "y": 141,
            "t_ms": 547
          }
        ],
        "target_element": "div",
        "target_bbox": {
          "x": 48,
          "y": 141,
          "width": 1169,
          "height": 16
        }
      }
    },
    {
      "event_id": 14,
      "timestamp_ms": 554,
      "type": "mousemove",
      "data": {
        "path": [
          {
            "x": 858,
            "y": 141,
            "t_ms": 547
          },
          {
            "x": 866,
            "y": 133,
            "t_ms": 554
          }
        ],
        "target_element": "section",
        "target_bbox": {
          "x": 0,
          "y": 77,
          "width": 1265,
          "height": 257
        }
      }
    },
    {
      "event_id": 15,
      "timestamp_ms": 560,
      "type": "mousemove",
      "data": {
        "path": [
          {
            "x": 866,
            "y": 133,
            "t_ms": 554
          },
          {
            "x": 875,
            "y": 122,
            "t_ms": 560
          }
        ],
        "target_element": "section",
        "target_bbox": {
          "x": 0,
          "y": 77,
          "width": 1265,
          "height": 257
        }
      }
    },
    {
      "event_id": 16,
      "timestamp_ms": 567,
      "type": "mousemove",
      "data": {
        "path": [
          {
            "x": 875,
            "y": 122,
            "t_ms": 560
          },
          {
            "x": 887,
            "y": 110,
            "t_ms": 567
          }
        ],
        "target_element": "section",
        "target_bbox": {
          "x": 0,
          "y": 77,
          "width": 1265,
          "height": 257
        }
      }
    },
    {
      "event_id": 17,
      "timestamp_ms": 574,
      "type": "mousemove",
      "data": {
        "path": [
          {
            "x": 887,
            "y": 110,
            "t_ms": 567
          },
          {
            "x": 900,
            "y": 95,
            "t_ms": 574
          }
        ],
        "target_element": "section",
        "target_bbox": {
          "x": 0,
          "y": 77,
          "width": 1265,
          "height": 257
        }
      }
    },
    {
      "event_id": 18,
      "timestamp_ms": 581,
      "type": "mousemove",
      "data": {
        "path": [
          {
            "x": 900,
            "y": 95,
            "t_ms": 574
          },
          {
            "x": 919,
            "y": 77,
            "t_ms": 581
          }
        ],
        "target_element": "section",
        "target_bbox": {
          "x": 0,
          "y": 77,
          "width": 1265,
          "height": 257
        }
      }
    },
    {
      "event_id": 19,
      "timestamp_ms": 589,
      "type": "mousemove",
      "data": {
        "path": [
          {
            "x": 919,
            "y": 77,
            "t_ms": 581
          },
          {
            "x": 936,
            "y": 61,
            "t_ms": 589
          }
        ],
        "target_element": "header",
        "target_bbox": {
          "x": 0,
          "y": 0,
          "width": 1265,
          "height": 77
        }
      }
    },
    {
      "event_id": 20,
      "timestamp_ms": 596,
      "type": "mousemove",
      "data": {
        "path": [
          {
            "x": 936,
            "y": 61,
            "t_ms": 589
          },
          {
            "x": 956,
            "y": 45,
            "t_ms": 596
          }
        ],
        "target_element": "header",
        "target_bbox": {
          "x": 0,
          "y": 0,
          "width": 1265,
          "height": 77
        }
      }
    },
    {
      "event_id": 21,
      "timestamp_ms": 603,
      "type": "mousemove",
      "data": {
        "path": [
          {
            "x": 956,
            "y": 45,
            "t_ms": 596
          },
          {
            "x": 972,
            "y": 34,
            "t_ms": 603
          }
        ],
        "target_element": "header",
        "target_bbox": {
          "x": 0,
          "y": 0,
          "width": 1265,
          "height": 77
        }
      }
    },
    {
      "event_id": 22,
      "timestamp_ms": 610,
      "type": "mousemove",
      "data": {
        "path": [
          {
            "x": 972,
            "y": 34,
            "t_ms": 603
          },
          {
            "x": 989,
            "y": 24,
            "t_ms": 610
          }
        ],
        "target_element": "header",
        "target_bbox": {
          "x": 0,
          "y": 0,
          "width": 1265,
          "height": 77
        }
      }
    },
    {
      "event_id": 23,
      "timestamp_ms": 617,
      "type": "mousemove",
      "data": {
        "path": [
          {
            "x": 989,
            "y": 24,
            "t_ms": 610
          },
          {
            "x": 1002,
            "y": 17,
            "t_ms": 617
          }
        ],
        "target_element": "header",
        "target_bbox": {
          "x": 0,
          "y": 0,
          "width": 1265,
          "height": 77
        }
      }
    },
    {
      "event_id": 24,
      "timestamp_ms": 623,
      "type": "mousemove",
      "data": {
        "path": [
          {
            "x": 1002,
            "y": 17,
            "t_ms": 617
          },
          {
            "x": 1013,
            "y": 12,
            "t_ms": 623
          }
        ],
        "target_element": "header",
        "target_bbox": {
          "x": 0,
          "y": 0,
          "width": 1265,
          "height": 77
        }
      }
    },
    {
      "event_id": 25,
      "timestamp_ms": 631,
      "type": "mousemove",
      "data": {
        "path": [
          {
            "x": 1013,
            "y": 12,
            "t_ms": 623
          },
          {
            "x": 1024,
            "y": 6,
            "t_ms": 631
          }
        ],
        "target_element": "header",
        "target_bbox": {
          "x": 0,
          "y": 0,
          "width": 1265,
          "height": 77
        }
      }
    },
    {
      "event_id": 26,
      "timestamp_ms": 637,
      "type": "mousemove",
      "data": {
        "path": [
          {
            "x": 1024,
            "y": 6,
            "t_ms": 631
          },
          {
            "x": 1034,
            "y": 3,
            "t_ms": 637
          }
        ],
        "target_element": "header",
        "target_bbox": {
          "x": 0,
          "y": 0,
          "width": 1265,
          "height": 77
        }
      }
    },
    {
      "event_id": 27,
      "timestamp_ms": 1392,
      "type": "scroll",
      "data": {
        "start_y": 0,
        "end_y": 220,
        "duration_ms": 150,
        "steps": [
          {
            "y": 220,
            "t_ms": 1242
          }
        ]
      }
    },
    {
      "event_id": 28,
      "timestamp_ms": 1561,
      "type": "scroll",
      "data": {
        "start_y": 220,
        "end_y": 306,
        "duration_ms": 152,
        "steps": [
          {
            "y": 306,
            "t_ms": 1409
          }
        ]
      }
    },
    {
      "event_id": 29,
      "timestamp_ms": 1996,
      "type": "scroll",
      "data": {
        "start_y": 306,
        "end_y": 849,
        "duration_ms": 380,
        "steps": [
          {
            "y": 468,
            "t_ms": 1616
          },
          {
            "y": 602,
            "t_ms": 1706
          },
          {
            "y": 849,
            "t_ms": 1846
          }
        ]
      }
    },
    {
      "event_id": 30,
      "timestamp_ms": 2113,
      "type": "scroll",
      "data": {
        "start_y": 849,
        "end_y": 0,
        "duration_ms": 17,
        "steps": [
          {
            "y": 0,
            "t_ms": 2096
          }
        ]
      }
    }
  ]
}